rpcpy/__init__.py
rpcpy/__version__.py
rpcpy/application.py
rpcpy/client.py
rpcpy/exceptions.py
rpcpy/openapi.py
rpcpy/serializers.py
rpc.py-0.6.0.dist-info/LICENSE
rpc.py-0.6.0.dist-info/WHEEL
rpc.py-0.6.0.dist-info/METADATA
rpc.py-0.6.0.dist-info/RECORD
