Metadata-Version: 2.1
Name: rpc.py
Version: 0.6.0
Summary: An fast and powerful RPC framework based on ASGI/WSGI.
Home-page: https://github.com/abersheeran/rpc.py
License: Apache-2.0
Author: abersheeran
Author-email: me@abersheeran.com
Requires-Python: >=3.7,<4.0
Classifier: License :: OSI Approved :: Apache Software License
Classifier: Programming Language :: Python :: 3
Classifier: Programming Language :: Python :: 3.10
Classifier: Programming Language :: Python :: 3.7
Classifier: Programming Language :: Python :: 3.8
Classifier: Programming Language :: Python :: 3.9
Classifier: Programming Language :: Python :: Implementation :: CPython
Classifier: Programming Language :: Python :: Implementation :: PyPy
Classifier: Topic :: Internet :: WWW/HTTP
Classifier: Topic :: Internet :: WWW/HTTP :: WSGI :: Application
Classifier: Typing :: Typed
Provides-Extra: cbor
Provides-Extra: client
Provides-Extra: full
Provides-Extra: msgpack
Provides-Extra: type
Requires-Dist: baize
Requires-Dist: cbor2 (>=5.2.0,<6.0.0); extra == "cbor" or extra == "full"
Requires-Dist: httpx (>=0.22.0,<0.23.0); extra == "client" or extra == "full"
Requires-Dist: msgpack (>=1.0.0,<2.0.0); extra == "full" or extra == "msgpack"
Requires-Dist: pydantic (>=1.9,<2.0); extra == "full" or extra == "type"
Requires-Dist: typing-extensions; python_version < "3.8"
Project-URL: Repository, https://github.com/abersheeran/rpc.py
